policypools/__init__.py
policypools/_process.py
policypools/_thread.py
policypools/base.py
policypools-1.0.0.dist-info/DESCRIPTION.rst
policypools-1.0.0.dist-info/METADATA
policypools-1.0.0.dist-info/RECORD
policypools-1.0.0.dist-info/WHEEL
policypools-1.0.0.dist-info/metadata.json
policypools-1.0.0.dist-info/top_level.txt
