Metadata-Version: 2.0
Name: policypools
Version: 1.0.0
Summary: Provides thread and process pools with policies
Home-page: https://github.com/alexanderepstein/policypools
Author: Alexander Epstein
Author-email: alexanderepstein@tuta.io
License: MIT
Keywords: multithreading,policy,thread-pool,thread-policypools,policies
Platform: UNKNOWN
Classifier: License :: OSI Approved :: MIT License
Classifier: Programming Language :: Python :: 3
Classifier: Programming Language :: Python :: 3.3
Classifier: Programming Language :: Python :: 3.4
Classifier: Programming Language :: Python :: 3.5
Classifier: Programming Language :: Python :: 3.6
Classifier: Programming Language :: Python :: Implementation :: PyPy
